[
  {
    "id": "jacket",
    "title": "Men'S Slim-Fit Casual Jacket with Italian Flag & Italia Print",
    "price": "AED 4.06",
    "note": "\u26a0\ufe0f The discount may vary.",
    "img": "https://img.kwcdn.com/product/Fancyalgo/VirtualModelMatting/2c285ca01496d1b02b1fc96bce33026e.jpg?imageView2/2/w/600/q/80",
    "adImg": "https://via.placeholder.com/600x150/ff6600/ffffff?text=Jacket+Promo",
    "link": "https://temu.to/k/erouery6gun"
  },
  {
    "id": "shoes",
    "title": "Men's Professional Basketball Shoes",
    "price": "AED 4.38",
    "note": "\u26a0\ufe0f The discount may vary.",
    "img": "https://img.kwcdn.com/product/Fancyalgo/VirtualModelMatting/1e480ec03b17e9d8b679b3e6c222ef46.jpg?imageView2/2/w/600/q/80",
    "adImg": "https://via.placeholder.com/600x150/33cc33/ffffff?text=Shoes+Deal",
    "link": "https://temu.to/k/e6pkeg1mddb"
  },
  {
    "id": "samsung-case",
    "title": "Compatible with Samsung Note 10 20 9 S9 S10 S10E+ Plus Lite Ultra",
    "price": "AED 14.19",
    "note": "\u26a0\ufe0f The discount may vary.",
    "img": "https://img.kwcdn.com/product/Fancyalgo/VirtualModelMatting/3b7e1a2c4d1b2a8f8c1d2e3f.jpg?imageView2/2/w/600/q/80",
    "adImg": "https://via.placeholder.com/600x150/0066ff/ffffff?text=Samsung+Case+Deal",
    "link": "https://temu.to/k/efhxo9a9ab7"
  }
]